pyhtklib/__init__.py
pyhtklib/cli.py
pyhtklib/measure_setup.py
pyhtklib/database/__init__.py
pyhtklib/database/es.py
pyhtklib/dlls/x64/HTDisplayDll.dll
pyhtklib/dlls/x64/HTHardDll.dll
pyhtklib/dlls/x64/HTSoftDll.dll
pyhtklib/dlls/x64/MeasDll.dll
pyhtklib/osciloskop/LICENSE
pyhtklib/osciloskop/__init__.py
pyhtklib/osciloskop/core.py
pyhtklib/osciloskop/data.py
pyhtklib/osciloskop/jobs.py
pyhtklib/osciloskop/setup.py
pyhtklib/dlls/x64/HTDisplayDll.dll
pyhtklib/dlls/x64/HTHardDll.dll
pyhtklib/dlls/x64/HTSoftDll.dll
pyhtklib/dlls/x64/MeasDll.dll
pyhtklib-0.1.7.dist-info/METADATA
pyhtklib-0.1.7.dist-info/WHEEL
pyhtklib-0.1.7.dist-info/entry_points.txt
pyhtklib-0.1.7.dist-info/licenses/LICENSE
pyhtklib-0.1.7.dist-info/RECORD
