Metadata-Version: 2.4
Name: PyHTKLib
Version: 0.1.7
Summary: Python library for Hantek oscilloscope control and data acquisition, specifically designed for the Hantek6254BC model
Project-URL: Homepage, https://github.com/sarasimkulakova/PyHTKLib
Project-URL: Bug Tracker, https://github.com/sarasimkulakova/PyHTKLib/issues
Project-URL: Documentation, https://github.com/sarasimkulakova/PyHTKLib#readme
Project-URL: Changelog, https://github.com/sarasimkulakova/PyHTKLib/blob/main/CHANGELOG.md
Author-email: Sára Šimkuláková <sara.simkulak@gmail.com>
License-Expression: MIT
License-File: LICENSE
Keywords: data-acquisition,hantek,measurement,oscilloscope
Classifier: Development Status :: 4 - Beta
Classifier: Intended Audience :: Science/Research
Classifier: License :: OSI Approved :: MIT License
Classifier: Operating System :: Microsoft :: Windows
Classifier: Programming Language :: Python :: 3
Classifier: Programming Language :: Python :: 3.8
Classifier: Programming Language :: Python :: 3.9
Classifier: Programming Language :: Python :: 3.10
Classifier: Programming Language :: Python :: 3.11
Classifier: Topic :: Scientific/Engineering
Classifier: Topic :: Software Development :: Libraries :: Python Modules
Requires-Python: >=3.8
Requires-Dist: click>=8.0.0
Requires-Dist: pyyaml>=6.0
Requires-Dist: urllib3>=2.0.0
Provides-Extra: dev
Requires-Dist: black>=21.0; extra == 'dev'
Requires-Dist: flake8>=3.9; extra == 'dev'
Requires-Dist: isort>=5.0; extra == 'dev'
Requires-Dist: pytest>=6.0; extra == 'dev'
